CHANGES.rst
LICENSE.txt
README.rst
setup.cfg
setup.py
django_pq.egg-info/PKG-INFO
django_pq.egg-info/SOURCES.txt
django_pq.egg-info/dependency_links.txt
django_pq.egg-info/requires.txt
django_pq.egg-info/top_level.txt
pq/__init__.py
pq/admin.py
pq/decorators.py
pq/exceptions.py
pq/flow.py
pq/job.py
pq/models.py
pq/queue.py
pq/timeouts.py
pq/utils.py
pq/worker.py
pq/compat/__init__.py
pq/contrib/__init__.py
pq/contrib/sentry.py
pq/management/__init__.py
pq/management/commands/__init__.py
pq/management/commands/pqbenchmark.py
pq/management/commands/pqcreate.py
pq/management/commands/pqenqueue.py
pq/management/commands/pqschedule.py
pq/management/commands/pqworker.py
pq/migrations/0001_initial.py
pq/migrations/0002_auto__add_field_queue_connection__add_field_queue_idempotent__add_fiel.py
pq/migrations/0003_auto__add_field_worker_heartbeat.py
pq/migrations/__init__.py