Metadata-Version: 1.1
Name: django-pq
Version: 0.3.2
Summary: A task queue based on the RQ api with a postgresql backend
Home-page: https://github.com/bretth/django-pq
Author: Brett Haydon
Author-email: brett@haydon.id.au
License: BSD
Keywords: django
Platform: UNKNOWN
Classifier: Development Status :: 3 - Alpha
Classifier: Framework :: Django
Classifier: Intended Audience :: Developers
Classifier: License :: OSI Approved :: BSD License
Classifier: Operating System :: OS Independent
Classifier: Programming Language :: Python :: 2.7
Classifier: Programming Language :: Python :: 3.3
Classifier: Topic :: System :: Distributed Computing
